atlas_mc_scanner/__about__.py
atlas_mc_scanner/__init__.py
atlas_mc_scanner/cli.py
atlas_mc_scanner/common.py
atlas_mc_scanner/decays.py
atlas_mc_scanner/find_containers.py
atlas_mc_scanner/list_particles.py
atlas_mc_scanner-1.0.1.dist-info/METADATA
atlas_mc_scanner-1.0.1.dist-info/WHEEL
atlas_mc_scanner-1.0.1.dist-info/entry_points.txt
atlas_mc_scanner-1.0.1.dist-info/licenses/LICENSE.txt
atlas_mc_scanner-1.0.1.dist-info/RECORD
